cron_task.py
cron_task-0.1.1.dist-info/METADATA
cron_task-0.1.1.dist-info/WHEEL
cron_task-0.1.1.dist-info/RECORD
