Metadata-Version: 2.1
Name: cron-task
Version: 0.1.1
Summary: Script runner based on interval
Home-page: https://github.com/nsiregar/runner
License: MIT
Author: Ngalim Siregar
Author-email: ngalim.siregar@gmail.com
Requires-Python: >=3.8,<4.0
Classifier: License :: OSI Approved :: MIT License
Classifier: Programming Language :: Python :: 3
Classifier: Programming Language :: Python :: 3.8
Classifier: Programming Language :: Python :: 3.9
Classifier: Programming Language :: Python :: 3.10
Classifier: Programming Language :: Python :: 3.11
Classifier: Programming Language :: Python :: 3.12
Project-URL: Repository, https://github.com/nsiregar/runner
